<?xml version="1.0" encoding="utf-8"?><toc><breadcrumbs><li><a href="28b8d0e6-785d-420a-8d17-e13b2dda1c65.htm">Docs</a></li><li><a href="4526de44-cf1e-2908-9abf-ffdae57628f3.htm">Interface<wbr />Main</a></li></breadcrumbs><tocItems><li><a id="98a331e5-19fd-434a-db15-febdce6a5438" class="has-submenu" href="98a331e5-19fd-434a-db15-febdce6a5438.htm"><span data-tocFile="../toc/IDAK.xml" class="icon toggle" onclick="ToggleExpandCollapse(this); return false;"><i class="fa fa-angle-right"> </i></span>Load<wbr />References</a><ul class="toc-menu is-hidden"> </ul></li><li><a id="a11b9905-1f6c-d36f-e055-652aa2507dd0" class="has-submenu" href="a11b9905-1f6c-d36f-e055-652aa2507dd0.htm"><span data-tocFile="../toc/IDBK.xml" class="icon toggle" onclick="ToggleExpandCollapse(this); return false;"><i class="fa fa-angle-right"> </i></span>Main<wbr />Forms</a><ul class="toc-menu is-hidden"> </ul></li><li><a id="0542e5d5-2947-328f-2d5c-0199895f60a6" class="has-submenu" href="0542e5d5-2947-328f-2d5c-0199895f60a6.htm"><span data-tocFile="../toc/IDCK.xml" class="icon toggle" onclick="ToggleExpandCollapse(this); return false;"><i class="fa fa-angle-right"> </i></span>Program</a><ul class="toc-menu is-hidden"> </ul></li><li><a id="ef07e983-5de8-d656-776a-105186d33f88" class="has-submenu" href="ef07e983-5de8-d656-776a-105186d33f88.htm"><span data-tocFile="../toc/IDDK.xml" class="icon toggle" onclick="ToggleExpandCollapse(this); return false;"><i class="fa fa-angle-right"> </i></span>Return<wbr />Log<wbr />Forms</a><ul class="toc-menu is-hidden"> </ul></li></tocItems></toc>